{
    "relatedPosts": [
        {
            "url": "\/health\/zheltye-pyatna-na-kozhe",
            "img": "https:\/\/cdn-icons-png.flaticon.com\/128\/5727\/5727010.png",
            "title": "Желтые пятна на коже – причины, виды, диагностика и лечение",
            "classes": "health"
        },
        {
            "url": "\/health\/gipertonus-matki",
            "img": "https:\/\/cdn-icons-png.flaticon.com\/128\/2302\/2302743.png",
            "title": "Гипертонус матки при беременности – симптомы, причины, признаки, диагностика и лечение",
            "classes": "health"
        },
        {
            "url": "\/health\/pulpit-zuba",
            "img": "https:\/\/cdn-icons-png.flaticon.com\/128\/3501\/3501475.png",
            "title": "🦷 Пульпит: причины, симптомы, виды, диагностика и лечение",
            "classes": "health"
        },
        {
            "url": "\/health\/oligomenoreya",
            "img": "https:\/\/cdn-icons-png.flaticon.com\/128\/5089\/5089602.png",
            "title": "Олигоменорея – причины, симптомы, виды, диагностика и лечение заболевания у женщин",
            "classes": "health"
        },
        {
            "url": "\/health\/vospalenie-soska",
            "img": "https:\/\/cdn-icons-png.flaticon.com\/128\/8604\/8604378.png",
            "title": "Воспаление соска (телит) – симптомы, причины и лечение",
            "classes": "health"
        },
        {
            "url": "\/health\/razryv-svyazok",
            "img": "https:\/\/cdn-icons-png.flaticon.com\/128\/7220\/7220390.png",
            "title": "Разрыв связок – симптомы, признаки, причины и лечение заболевания",
            "classes": "health"
        }
    ],
    "tags": [
        {
            "name": "Температура тела",
            "url": "#"
        },
        {
            "name": "Лихорадка",
            "url": "#"
        },
        {
            "name": "Жар",
            "url": "#"
        },
        {
            "name": "Симптомы",
            "url": "#"
        },
        {
            "name": "Причины",
            "url": "#"
        },
        {
            "name": "Лечение",
            "url": "#"
        },
        {
            "name": "Диагностика",
            "url": "#"
        },
        {
            "name": "Инфекция",
            "url": "#"
        },
        {
            "name": "Здоровье",
            "url": "#"
        },
        {
            "name": "Градусник",
            "url": "#"
        }
    ]
}