{
    "relatedPosts": [
        {
            "url": "\/health\/adenokarcinoma-matki",
            "img": "https:\/\/cdn-icons-png.flaticon.com\/128\/2309\/2309130.png",
            "title": "Аденокарцинома матки – причины, симптомы, диагностика и лечение, прогноз",
            "classes": "health"
        },
        {
            "url": "\/health\/bol-v-temeni",
            "img": "https:\/\/cdn-icons-png.flaticon.com\/128\/5730\/5730290.png",
            "title": "Боль в темени – причины, симптомы, виды, диагностика и лечение",
            "classes": "health"
        },
        {
            "url": "\/health\/rak-yaichka",
            "img": "https:\/\/cdn-icons-png.flaticon.com\/128\/4615\/4615318.png",
            "title": "Рак яичка – симптомы, признаки, причины, диагностика и лечение у мужчин",
            "classes": "health"
        },
        {
            "url": "\/health\/fibromioma-matki",
            "img": "https:\/\/cdn-icons-png.flaticon.com\/128\/2309\/2309130.png",
            "title": "Фибромиома матки – причины, симптомы, виды, диагностика и лечение заболевания у женщин",
            "classes": "health"
        },
        {
            "url": "\/health\/menorragiya",
            "img": "https:\/\/cdn-icons-png.flaticon.com\/128\/5089\/5089595.png",
            "title": "Меноррагия – что это, причины, симптомы, диагностика и лечение у женщин",
            "classes": "health"
        },
        {
            "url": "\/health\/ostryy-rinit",
            "img": "https:\/\/cdn-icons-png.flaticon.com\/128\/3073\/3073996.png",
            "title": "Острый ринит – причины, симптомы, виды, диагностика и лечение взрослых",
            "classes": "health"
        }
    ],
    "tags": [
        {
            "name": "Анкилоз зуба",
            "url": "#"
        },
        {
            "name": "Зубы",
            "url": "#"
        },
        {
            "name": "Сращение",
            "url": "#"
        },
        {
            "name": "Симптомы",
            "url": "#"
        },
        {
            "name": "Причины",
            "url": "#"
        },
        {
            "name": "Лечение",
            "url": "#"
        },
        {
            "name": "Диагностика",
            "url": "#"
        },
        {
            "name": "Стоматология",
            "url": "#"
        },
        {
            "name": "Ортодонтия",
            "url": "#"
        }
    ]
}