{
    "relatedPosts": [
        {
            "url": "\/health\/evstahiit",
            "img": "https:\/\/cdn-icons-png.flaticon.com\/128\/6598\/6598353.png",
            "title": "Евстахиит – причины, симптомы, виды, диагностика и лечение у взрослых",
            "classes": "health"
        },
        {
            "url": "\/health\/gnoynyy-periostit",
            "img": "https:\/\/cdn-icons-png.flaticon.com\/128\/2725\/2725614.png",
            "title": "Гнойный периостит – причины, симптомы, диагностика и лечение заболевания",
            "classes": "health"
        },
        {
            "url": "\/health\/rinofaringit",
            "img": "https:\/\/cdn-icons-png.flaticon.com\/128\/2660\/2660111.png",
            "title": "Ринофарингит – симптомы, причины, диагностика и лечение болезни у взрослых",
            "classes": "health"
        },
        {
            "url": "\/health\/osteomalyaciya",
            "img": "https:\/\/cdn-icons-png.flaticon.com\/128\/3066\/3066996.png",
            "title": "Остеомаляция – причины, симптомы, диагностика и лечение",
            "classes": "health"
        },
        {
            "url": "\/health\/abscess-moshonki",
            "img": "https:\/\/cdn-icons-png.flaticon.com\/128\/4145\/4145572.png",
            "title": "Абсцесс мошонки – причины, симптомы, диагностика и лечение болезни у взрослых",
            "classes": "health"
        },
        {
            "url": "\/health\/toksikoz-pri-beremennosti",
            "img": "https:\/\/cdn-icons-png.flaticon.com\/128\/5730\/5730148.png",
            "title": "Токсикоз при беременности на ранних сроках – симптомы, причины, диагностика и лечение",
            "classes": "health"
        }
    ],
    "tags": [
        {
            "name": "Боль в носу",
            "url": "#"
        },
        {
            "name": "Нос",
            "url": "#"
        },
        {
            "name": "Симптомы",
            "url": "#"
        },
        {
            "name": "Причины",
            "url": "#"
        },
        {
            "name": "Лечение",
            "url": "#"
        },
        {
            "name": "Диагностика",
            "url": "#"
        },
        {
            "name": "Ринит",
            "url": "#"
        },
        {
            "name": "Синусит",
            "url": "#"
        },
        {
            "name": "Травма",
            "url": "#"
        },
        {
            "name": "ЛОР",
            "url": "#"
        }
    ]
}