{
    "relatedPosts": [
        {
            "url": "\/health\/gribkovaya-pnevmoniya",
            "img": "https:\/\/cdn-icons-png.flaticon.com\/128\/3654\/3654698.png",
            "title": "Грибковая пневмония – причины, симптомы, виды, диагностика и лечение заболевания у взрослых",
            "classes": "health"
        },
        {
            "url": "\/health\/gipermetropiya-dalnozorkost",
            "img": "https:\/\/cdn-icons-png.flaticon.com\/128\/4937\/4937354.png",
            "title": "Гиперметропия (дальнозоркость) – причины, симптомы, степени, диагностика и лечение заболевания",
            "classes": "health"
        },
        {
            "url": "\/health\/artroz-tazobedrennogo-sustava",
            "img": "https:\/\/cdn-icons-png.flaticon.com\/128\/4702\/4702258.png",
            "title": "Артроз тазобедренного сустава – степени, симптомы, стадии и лечение заболевания",
            "classes": "health"
        },
        {
            "url": "\/health\/poterya-obonyaniya",
            "img": "https:\/\/cdn-icons-png.flaticon.com\/128\/3073\/3073996.png",
            "title": "Потеря обоняния (аносмия) – причины, диагностика и лечение у взрослых",
            "classes": "health"
        },
        {
            "url": "\/health\/allergicheskij-rinit",
            "img": "https:\/\/cdn-icons-png.flaticon.com\/128\/5730\/5730304.png",
            "title": "Аллергический ринит – причины, симптомы, виды, диагностика и лечение заболевания",
            "classes": "health"
        },
        {
            "url": "\/health\/snizhenie-appetita",
            "img": "https:\/\/cdn-icons-png.flaticon.com\/128\/5705\/5705426.png",
            "title": "Снижение аппетита – причины симптома, виды, диагностика и лечение у взрослых",
            "classes": "health"
        }
    ],
    "tags": [
        {
            "name": "Липома",
            "url": "#"
        },
        {
            "name": "Жировик",
            "url": "#"
        },
        {
            "name": "Кожа",
            "url": "#"
        },
        {
            "name": "Опухоль",
            "url": "#"
        },
        {
            "name": "Симптомы",
            "url": "#"
        },
        {
            "name": "Причины",
            "url": "#"
        },
        {
            "name": "Лечение",
            "url": "#"
        },
        {
            "name": "Диагностика",
            "url": "#"
        },
        {
            "name": "Дерматология",
            "url": "#"
        }
    ]
}