{
    "relatedPosts": [
        {
            "url": "\/health\/artroz-tazobedrennogo-sustava",
            "img": "https:\/\/cdn-icons-png.flaticon.com\/128\/4702\/4702258.png",
            "title": "Артроз тазобедренного сустава – степени, симптомы, стадии и лечение заболевания",
            "classes": "health"
        },
        {
            "url": "\/health\/ostraya-pochechnaya-nedostatochnost",
            "img": "https:\/\/cdn-icons-png.flaticon.com\/128\/2660\/2660065.png",
            "title": "Острая почечная недостаточность – причины, симптомы, стадии, диагностика и лечение заболевания",
            "classes": "health"
        },
        {
            "url": "\/health\/miopiya-blizorukost",
            "img": "https:\/\/cdn-icons-png.flaticon.com\/128\/4937\/4937354.png",
            "title": "Миопия (близорукость) – причины, симптомы, степени, диагностика и лечение заболевания",
            "classes": "health"
        },
        {
            "url": "\/health\/episklerit-glaza",
            "img": "https:\/\/cdn-icons-png.flaticon.com\/128\/4937\/4937372.png",
            "title": "Эписклерит глаза – причины, симптомы, признаки, диагностика и лечение заболевания",
            "classes": "health"
        },
        {
            "url": "\/health\/rinofaringit",
            "img": "https:\/\/cdn-icons-png.flaticon.com\/128\/2660\/2660111.png",
            "title": "Ринофарингит – симптомы, причины, диагностика и лечение болезни у взрослых",
            "classes": "health"
        },
        {
            "url": "\/health\/rvota-pri-beremennosti",
            "img": "https:\/\/cdn-icons-png.flaticon.com\/128\/5730\/5730148.png",
            "title": "Рвота при беременности – причины, симптомы, виды, диагностика и лечение",
            "classes": "health"
        }
    ],
    "tags": [
        {
            "name": "Ахиллобурсит",
            "url": "#"
        },
        {
            "name": "Ахиллово сухожилие",
            "url": "#"
        },
        {
            "name": "Пятка",
            "url": "#"
        },
        {
            "name": "Воспаление",
            "url": "#"
        },
        {
            "name": "Симптомы",
            "url": "#"
        },
        {
            "name": "Причины",
            "url": "#"
        },
        {
            "name": "Лечение",
            "url": "#"
        },
        {
            "name": "Диагностика",
            "url": "#"
        },
        {
            "name": "Бурсит",
            "url": "#"
        },
        {
            "name": "Ортопедия",
            "url": "#"
        }
    ]
}